justdeepit/__init__.py
justdeepit/utils.py
justdeepit/app/__init__.py
justdeepit/app/app.py
justdeepit/app/appbase.py
justdeepit/app/appis.py
justdeepit/app/appod.py
justdeepit/app/appsod.py
justdeepit/app/static/jquery-3.6.0.min.js
justdeepit/app/static/jquery-3.6.0.min.map
justdeepit/app/static/styles.css
justdeepit/app/static/tree.jquery.js
justdeepit/app/static/tree.jquery.js.map
justdeepit/app/static/utils.js
justdeepit/app/templates/index.html
justdeepit/app/templates/module.html
justdeepit/app/templates/shutdown.html
justdeepit/models/__init__.py
justdeepit/models/abstract.py
justdeepit/models/instance_segment.py
justdeepit/models/object_detect.py
justdeepit/models/salient_object_detect.py
justdeepit/models/utils/__init__.py
justdeepit/models/utils/data.py
justdeepit/models/utils/mmdetbase.py
justdeepit/models/utils/u2net.py
justdeepit/models/utils/unet.py
justdeepit/src/font/NotoSans-Medium.ttf
justdeepit/src/font/OFL.txt
JustDeepIt-0.2.1.dist-info/LICENSE
JustDeepIt-0.2.1.dist-info/METADATA
JustDeepIt-0.2.1.dist-info/WHEEL
JustDeepIt-0.2.1.dist-info/entry_points.txt
JustDeepIt-0.2.1.dist-info/top_level.txt
JustDeepIt-0.2.1.dist-info/zip-safe
JustDeepIt-0.2.1.dist-info/RECORD
