Metadata-Version: 2.1
Name: JustDeepIt
Version: 0.2.1
Summary: a GUI tool for object detection and segmentation based on deep learning
Home-page: https://github.com/biunit/JustDeepIt
Author: Jianqiang Sun
Author-email: sun@biunit.dev
License: MIT
Keywords: object detection,object segmentation
Classifier: Development Status :: 5 - Production/Stable
Classifier: Environment :: Console
Classifier: Environment :: X11 Applications
Classifier: Intended Audience :: Science/Research
Classifier: Natural Language :: English
Classifier: Operating System :: Unix
Classifier: Programming Language :: Python :: 3
Classifier: Topic :: Scientific/Engineering :: Image Recognition
License-File: LICENSE
Requires-Dist: tqdm
Requires-Dist: joblib
Requires-Dist: numpy
Requires-Dist: pandas
Requires-Dist: pillow
Requires-Dist: opencv-python >=4.5.1
Requires-Dist: scikit-image >=0.18.1
Requires-Dist: fastapi
Requires-Dist: uvicorn
Requires-Dist: jinja2
Requires-Dist: python-multipart
Requires-Dist: torch >=1.8
Requires-Dist: torchvision
Requires-Dist: openmim
